sigma/__init__.py
sigma/sigma_a.py
sigma/sigma_b.py
sigma_t-0.0.1.dist-info/LICENSE
sigma_t-0.0.1.dist-info/METADATA
sigma_t-0.0.1.dist-info/WHEEL
sigma_t-0.0.1.dist-info/top_level.txt
sigma_t-0.0.1.dist-info/RECORD
