Metadata-Version: 2.1
Name: sigma-t
Version: 0.0.1
Summary: six sigma project
Home-page: UNKNOWN
Author: AlanRick
Author-email: zs13128488417@gmail.com
License: UNKNOWN
Platform: UNKNOWN
Classifier: Programming Language :: Python :: 3
Classifier: License :: OSI Approved :: MIT License
Classifier: Operating System :: OS Independent
Requires-Python: >=3.6
